README.rst
setup.py
model_wrapper/__init__.py
model_wrapper/collator.py
model_wrapper/dataset.py
model_wrapper/log_utils.py
model_wrapper/utils.py
model_wrapper/wrapper.py
model_wrapper.egg-info/PKG-INFO
model_wrapper.egg-info/SOURCES.txt
model_wrapper.egg-info/dependency_links.txt
model_wrapper.egg-info/not-zip-safe
model_wrapper.egg-info/requires.txt
model_wrapper.egg-info/top_level.txt
model_wrapper/training/__init__.py
model_wrapper/training/_amp_support.py
model_wrapper/training/_support.py
model_wrapper/training/_trainer.py