Metadata-Version: 2.1
Name: model-wrapper
Version: 1.1.2
Summary: Model wrapper for Pytorch, which can training, predict, evaluate, etc.
Home-page: https://gitee.com/summry/model-wrapper
Author: summy
Author-email: fkfkfk2024@2925.com
License: UNKNOWN
Keywords: Pytorch,Training,AI,Machine learning,Deep learning,torch
Platform: UNKNOWN
Requires-Python: >=3.6
